factgenie/__init__.py
factgenie/analysis.py
factgenie/annotations.py
factgenie/app.py
factgenie/campaign.py
factgenie/colors.py
factgenie/crowdsourcing.py
factgenie/llm_campaign.py
factgenie/models.py
factgenie/utils.py
factgenie/workflows.py
factgenie/bin/__init__.py
factgenie/bin/run.py
factgenie/config/config_TEMPLATE.yml
factgenie/config/default_prompts.yml
factgenie/config/resources.yml
factgenie/config/crowdsourcing/example-tutorial.yaml
factgenie/config/crowdsourcing/example.yaml
factgenie/config/llm-eval/anthropic-example.yaml
factgenie/config/llm-eval/gemini-example.yaml
factgenie/config/llm-eval/ollama-example.yaml
factgenie/config/llm-eval/openai-example.yaml
factgenie/config/llm-eval/vertexai-example.yaml
factgenie/config/llm-gen/anthropic-example.yaml
factgenie/config/llm-gen/gemini-example.yaml
factgenie/config/llm-gen/ollama-example.yaml
factgenie/config/llm-gen/openai-example.yaml
factgenie/config/llm-gen/vertexai-example.yaml
factgenie/data/datasets_TEMPLATE.yml
factgenie/datasets/__init__.py
factgenie/datasets/basic.py
factgenie/datasets/dataset.py
factgenie/datasets/gsmarena.py
factgenie/datasets/hf_dataset.py
factgenie/datasets/ice_hockey.py
factgenie/datasets/logicnlg.py
factgenie/datasets/openweather.py
factgenie/datasets/owid.py
factgenie/datasets/propaganda_techniques.py
factgenie/datasets/quintd.py
factgenie/datasets/rotowire_shared_task.py
factgenie/datasets/wikidata.py
factgenie/iaa/__init__.py
factgenie/iaa/cli.py
factgenie/iaa/f1.py
factgenie/iaa/gamma.py
factgenie/iaa/pearson.py
factgenie/prompting/__init__.py
factgenie/prompting/model_apis.py
factgenie/prompting/registry.py
factgenie/prompting/text_processing.py
factgenie/prompting/transforms.py
factgenie/prompting/strategies/__init__.py
factgenie/prompting/strategies/base.py
factgenie/prompting/strategies/eval_default.py
factgenie/prompting/strategies/eval_raw_output.py
factgenie/prompting/strategies/eval_sentence_split.py
factgenie/prompting/strategies/gen_apply_template.py
factgenie-1.2.1.dist-info/licenses/LICENSE
factgenie-1.2.1.dist-info/METADATA
factgenie-1.2.1.dist-info/WHEEL
factgenie-1.2.1.dist-info/entry_points.txt
factgenie-1.2.1.dist-info/top_level.txt
factgenie-1.2.1.dist-info/RECORD
