Metadata-Version: 2.4
Name: factgenie
Version: 1.2.1
Summary: Lightweight self-hosted span annotation tool
Home-page: https://github.com/ufal/factgenie
Author: Zdenek Kasner, Ondrej Platek, Patricia Schmidtova, Dave Howcroft, Ondrej Dusek
Author-email: kasner@ufal.mff.cuni.cz
License: MIT
Classifier: Development Status :: 3 - Alpha
Classifier: Programming Language :: Python :: 3.9
Classifier: Programming Language :: Python :: 3.10
Classifier: Programming Language :: Python :: 3.11
Classifier: Intended Audience :: Science/Research
Classifier: Operating System :: POSIX :: Linux
Classifier: License :: OSI Approved :: MIT License
Classifier: Topic :: Scientific/Engineering :: Artificial Intelligence
Classifier: Topic :: Software Development :: Libraries :: Python Modules
Classifier: Typing :: Typed
Requires-Python: >=3.9
License-File: LICENSE
Requires-Dist: coloredlogs>=15.0.1
Requires-Dist: datasets>=2.9.0
Requires-Dist: Flask-SSE>=1.0.0
Requires-Dist: Flask>=2.2.2
Requires-Dist: flask_apscheduler>=1.12.4
Requires-Dist: json2table>=1.1.5
Requires-Dist: lxml>=5.3.0
Requires-Dist: Markdown>=3.7.0
Requires-Dist: natsort>=8.4.0
Requires-Dist: python-slugify>=8.0.4
Requires-Dist: PyYAML>=6.0.2
Requires-Dist: requests>=2.32.3
Requires-Dist: scipy>=1.14.1
Requires-Dist: tinyhtml>=1.2.0
Requires-Dist: litellm>=1.70.0
Requires-Dist: pydantic>=2.10.6
Requires-Dist: google-api-python-client>=2.16.0
Requires-Dist: google-cloud-aiplatform>=1.38
Requires-Dist: pygamma-agreement==0.5.9
Requires-Dist: matplotlib>=3.10.0
Requires-Dist: tabulate>=0.9.0
Requires-Dist: tenacity>=9.0.0
Requires-Dist: llm-sandbox>=0.3.12
Requires-Dist: fast-edit-distance>=1.2.2
Provides-Extra: dev
Requires-Dist: wheel>=0.44.0; extra == "dev"
Requires-Dist: ipdb; extra == "dev"
Requires-Dist: black==24.10.0; extra == "dev"
Requires-Dist: isort==5.13.2; extra == "dev"
Provides-Extra: test
Requires-Dist: pytest>=8.3.3; extra == "test"
Provides-Extra: deploy
Requires-Dist: gunicorn>=23.0.0; extra == "deploy"
Dynamic: author
Dynamic: author-email
Dynamic: classifier
Dynamic: description
Dynamic: description-content-type
Dynamic: home-page
Dynamic: license
Dynamic: license-file
Dynamic: provides-extra
Dynamic: requires-dist
Dynamic: requires-python
Dynamic: summary
